{"name":"Taslima1.GitHub.io","tagline":"Taslima Mansuri ","body":"### Software and Web Developer\r\n\r\nI am a Software Developer specialized in C#, PHP, .Net framework as well as frontend and backend skills creating web and desktop applications.\r\n\r\nHands on Experience with:\r\nC#, PHP, .Net, HTML5, CSS3, JavaScript, ASP.Net, Java, MySQL, MS SQL Server, JQuery, BootStrap, ASP.Net MVC framework\r\n\r\n\r\n\r\n\r\n\r\n\r\n\r\n\r\n\r\n\r\n","google":"","note":"Don't delete this file! It's used internally to help with page regeneration."}